fastdev/__init__.py
fastdev/constants.py
fastdev/extension.py
fastdev/py.typed
fastdev/csrc/ball_query/ball_query.cu
fastdev/csrc/ball_query/ball_query.h
fastdev/csrc/ball_query/ball_query_cpu.cpp
fastdev/csrc/ball_query/bindings.cpp
fastdev/csrc/knn/bindings.cpp
fastdev/csrc/knn/knn.cu
fastdev/csrc/knn/knn.h
fastdev/csrc/knn/knn_cpu.cpp
fastdev/csrc/point_mesh/bindings.cpp
fastdev/csrc/point_mesh/point_mesh.h
fastdev/csrc/point_mesh/point_mesh_cpu.cpp
fastdev/csrc/point_mesh/point_mesh_cuda.cu
fastdev/csrc/sample_farthest_points/bindings.cpp
fastdev/csrc/sample_farthest_points/sample_farthest_points.cu
fastdev/csrc/sample_farthest_points/sample_farthest_points.h
fastdev/csrc/sample_farthest_points/sample_farthest_points_cpu.cpp
fastdev/csrc/utils/cuda_utils.h
fastdev/csrc/utils/dispatch.cuh
fastdev/csrc/utils/float_math.cuh
fastdev/csrc/utils/geometry_v2.cuh
fastdev/csrc/utils/geometry_v2.h
fastdev/csrc/utils/index_utils.cuh
fastdev/csrc/utils/mat44.h
fastdev/csrc/utils/mink.cuh
fastdev/csrc/utils/vec3.h
fastdev/csrc/utils/warp_reduce.cuh
fastdev/datasets/__init__.py
fastdev/datasets/dexycb.py
fastdev/datasets/modelnet.py
fastdev/datasets/s3dis.py
fastdev/geom/__init__.py
fastdev/geom/ball_query.py
fastdev/geom/knn.py
fastdev/geom/sampling.py
fastdev/geom/utils.py
fastdev/geom/warp_meshes.py
fastdev/geom/warp_scene.py
fastdev/geom/warp_sdf_fns.py
fastdev/io/__init__.py
fastdev/io/archive.py
fastdev/io/download.py
fastdev/io/io.py
fastdev/io/handlers/__init__.py
fastdev/io/handlers/base_handler.py
fastdev/io/handlers/json_handler.py
fastdev/io/handlers/yaml_handler.py
fastdev/nn/__init__.py
fastdev/nn/mlp.py
fastdev/nn/point_transformer_v3.py
fastdev/nn/pointnet.py
fastdev/nn/pointnet2.py
fastdev/nn/spconv_unet.py
fastdev/robo/__init__.py
fastdev/robo/articulation.py
fastdev/robo/articulation_spec.py
fastdev/robo/curobo_utils.py
fastdev/robo/kinematics.py
fastdev/robo/single_articulation.py
fastdev/robo/warp_kinematics.py
fastdev/sim_webui/__init__.py
fastdev-0.2.2.dist-info/METADATA
fastdev-0.2.2.dist-info/WHEEL
fastdev-0.2.2.dist-info/top_level.txt
fastdev-0.2.2.dist-info/RECORD
