Metadata-Version: 2.4
Name: fastdev
Version: 0.2.2
Summary: Type less, code more
Author-email: Jianglong Ye <jianglong.yeh@gmail.com>
License: MIT
Project-URL: Homepage, https://fastdev.jianglongye.com/
Project-URL: Repository, https://github.com/jianglongye/fastdev
Classifier: Programming Language :: Python :: 3
Classifier: Programming Language :: Python :: 3.8
Classifier: Programming Language :: Python :: 3.9
Classifier: Programming Language :: Python :: 3.10
Classifier: Programming Language :: Python :: 3.11
Classifier: Programming Language :: Python :: 3.12
Classifier: License :: OSI Approved :: MIT License
Classifier: Operating System :: OS Independent
Requires-Python: >=3.8
Requires-Dist: ninja
Requires-Dist: typing-extensions
Requires-Dist: beartype
Requires-Dist: jaxtyping<=0.2.34
Requires-Dist: numpy<2.0.0
Requires-Dist: rich
Requires-Dist: msgspec[toml,yaml]
Requires-Dist: fsspec
Requires-Dist: universal_pathlib
Requires-Dist: huggingface_hub[cli,hf_transfer]
Provides-Extra: full
Requires-Dist: trimesh; extra == "full"
Requires-Dist: viser; extra == "full"
Requires-Dist: warp-lang==1.5.1; extra == "full"
Requires-Dist: einops; extra == "full"
Requires-Dist: transforms3d; extra == "full"
Requires-Dist: yourdfpy; extra == "full"
Requires-Dist: dm_control; extra == "full"
Requires-Dist: fpsample; extra == "full"
Requires-Dist: safetensors; extra == "full"
Requires-Dist: pin; extra == "full"
Provides-Extra: dev
Requires-Dist: build; extra == "dev"
Requires-Dist: twine; extra == "dev"
Requires-Dist: ipython; extra == "dev"
Requires-Dist: ruff; extra == "dev"
Requires-Dist: mypy; extra == "dev"
Requires-Dist: types-PyYAML; extra == "dev"
Requires-Dist: types-requests; extra == "dev"
Requires-Dist: pytest; extra == "dev"
Requires-Dist: xdoctest; extra == "dev"
Requires-Dist: pre-commit; extra == "dev"
Provides-Extra: doc
Requires-Dist: sphinx; extra == "doc"
Requires-Dist: furo; extra == "doc"
Requires-Dist: docutils; extra == "doc"
Requires-Dist: sphinx-autoapi; extra == "doc"
Requires-Dist: m2r2; extra == "doc"
